setup.py
ventriloquist/__init__.py
ventriloquist/loader.py
ventriloquist/page.py
ventriloquist/util.py
ventriloquist/wsgi_app.py
ventriloquist.egg-info/PKG-INFO
ventriloquist.egg-info/SOURCES.txt
ventriloquist.egg-info/dependency_links.txt
ventriloquist.egg-info/entry_points.txt
ventriloquist.egg-info/requires.txt
ventriloquist.egg-info/top_level.txt