Metadata-Version: 1.0
Name: ventriloquist
Version: 0.1
Summary: A super minimalist Jinja2 based (un-)CMS
Home-page: UNKNOWN
Author: Christopher Webber
Author-email: cwebber@dustycloud.org
License: MIT
Platform: UNKNOWN
